MANIFEST.in
requirements.txt
setup.py
wren/__init__.py
wren/client.py
wren/collection.py
wren.egg-info/PKG-INFO
wren.egg-info/SOURCES.txt
wren.egg-info/dependency_links.txt
wren.egg-info/requires.txt
wren.egg-info/top_level.txt