Metadata-Version: 1.1
Name: wren
Version: 0.3.5
Summary: Synchronous RESTful API consumer based on Requests
Home-page: https://github.com/bodylabs/wren
Author: Body Labs
Author-email: paul.melnikow@bodylabs.com
License: Apache 2
Platform: UNKNOWN
Classifier: Development Status :: 2 - Pre-Alpha
Classifier: Intended Audience :: Developers
Classifier: License :: OSI Approved :: Apache Software License
Classifier: Operating System :: OS Independent
Classifier: Programming Language :: Python
Classifier: Topic :: Software Development :: Libraries :: Python Modules
